mlpath/__init__.py
mlpath/mldir_cli/__init__.py
mlpath/mldir_cli/cli.py
mlpath/mldir_cli/__pycache__/__init__.cpython-39.pyc
mlpath/mldir_cli/__pycache__/cli.cpython-39.pyc
mlpath/mldir_cli/example-project/GIT-README.md
mlpath/mldir_cli/example-project/README.md
mlpath/mldir_cli/example-project/Sandbox.ipynb
mlpath/mldir_cli/example-project/requirements.txt
mlpath/mldir_cli/example-project/DataFiles/Dataset/Golden/1.jpeg
mlpath/mldir_cli/example-project/DataFiles/Dataset/Golden/2.jpeg
mlpath/mldir_cli/example-project/DataFiles/Dataset/Golden/3.jpeg
mlpath/mldir_cli/example-project/DataFiles/Dataset/Golden/4.jpeg
mlpath/mldir_cli/example-project/DataFiles/Dataset/Golden/5.jpeg
mlpath/mldir_cli/example-project/DataFiles/Dataset/Swedish/1.jpeg
mlpath/mldir_cli/example-project/DataFiles/Dataset/Swedish/2.jpeg
mlpath/mldir_cli/example-project/DataFiles/Dataset/Swedish/3.jpeg
mlpath/mldir_cli/example-project/DataFiles/Dataset/Swedish/4.jpeg
mlpath/mldir_cli/example-project/DataFiles/Dataset/Swedish/5.webp
mlpath/mldir_cli/example-project/DataPreparation/DataPreparation.ipynb
mlpath/mldir_cli/example-project/DataPreparation/Ingestion.py
mlpath/mldir_cli/example-project/DataPreparation/Preprocessing.py
mlpath/mldir_cli/example-project/FeatureExtraction/Fractal/Fractal.ipynb
mlpath/mldir_cli/example-project/FeatureExtraction/Fractal/Fractal.py
mlpath/mldir_cli/example-project/FeatureExtraction/Fractal/utils.py
mlpath/mldir_cli/example-project/FeatureExtraction/LBP/LBP.ipynb
mlpath/mldir_cli/example-project/FeatureExtraction/LBP/LBP.py
mlpath/mldir_cli/example-project/FeatureExtraction/Rand/Rand.ipynb
mlpath/mldir_cli/example-project/FeatureExtraction/Rand/Rand.py
mlpath/mldir_cli/example-project/ModelImplementation/CNN/CNN.py
mlpath/mldir_cli/example-project/ModelPipelines/CNN/CNN.ipynb
mlpath/mldir_cli/example-project/ModelPipelines/GradientBoost/Fractal-GB.ipynb
mlpath/mldir_cli/example-project/ModelPipelines/GradientBoost/Fractal-GB.md
mlpath-1.1.10.dist-info/LICENSE
mlpath-1.1.10.dist-info/METADATA
mlpath-1.1.10.dist-info/WHEEL
mlpath-1.1.10.dist-info/entry_points.txt
mlpath-1.1.10.dist-info/top_level.txt
mlpath-1.1.10.dist-info/RECORD
