Metadata-Version: 2.1
Name: mlpath
Version: 1.1.10
Summary: A lightweight api for machine and deep learning experiment logging in the form of a python library. 
Home-page: https://mlpath.readthedocs.io/
Author: Essam W., Abdullah A.
Author-email: essamwisam@outlook.com
License: GPLv3
Classifier: Intended Audience :: Developers
Classifier: License :: OSI Approved :: MIT License
Classifier: Programming Language :: Python
Classifier: Programming Language :: Python :: 3
Classifier: Programming Language :: Python :: 3.6
Classifier: Programming Language :: Python :: 3.7
Classifier: Programming Language :: Python :: 3.8
Classifier: Programming Language :: Python :: 3.9
Classifier: Operating System :: OS Independent
License-File: LICENSE
Requires-Dist: varname
Requires-Dist: click
Requires-Dist: flask
Requires-Dist: ipython
